{
  "recent": [
    {
      "battery_ok": 1,
      "channel": "C",
      "humidity": 57.0,
      "model": "Acurite-5n1",
      "observed_at": "2026-07-14 08:27:55 PDT",
      "rain_day_in": 0.0,
      "rain_mm": null,
      "rain_ytd_in": 46.682,
      "sensor_id": "1466",
      "temperature_c": null,
      "temperature_f": 74.7,
      "wind_avg_km_h": null,
      "wind_avg_mi_h": 0.0,
      "wind_dir_deg": 45.0
    },
    {
      "battery_ok": 1,
      "channel": "C",
      "humidity": 58.0,
      "model": "Acurite-5n1",
      "observed_at": "2026-07-14 08:22:55 PDT",
      "rain_day_in": 0.0,
      "rain_mm": null,
      "rain_ytd_in": 46.682,
      "sensor_id": "1466",
      "temperature_c": null,
      "temperature_f": 74.8,
      "wind_avg_km_h": null,
      "wind_avg_mi_h": 0.0,
      "wind_dir_deg": 67.5
    },
    {
      "battery_ok": 1,
      "channel": "C",
      "humidity": 54.0,
      "model": "Acurite-5n1",
      "observed_at": "2026-07-14 08:17:55 PDT",
      "rain_day_in": 0.0,
      "rain_mm": null,
      "rain_ytd_in": 46.682,
      "sensor_id": "1466",
      "temperature_c": null,
      "temperature_f": 75.0,
      "wind_avg_km_h": null,
      "wind_avg_mi_h": 0.0,
      "wind_dir_deg": 45.0
    },
    {
      "battery_ok": 1,
      "channel": "C",
      "humidity": 54.0,
      "model": "Acurite-5n1",
      "observed_at": "2026-07-14 08:12:55 PDT",
      "rain_day_in": 0.0,
      "rain_mm": null,
      "rain_ytd_in": 46.682,
      "sensor_id": "1466",
      "temperature_c": null,
      "temperature_f": 75.0,
      "wind_avg_km_h": null,
      "wind_avg_mi_h": 0.0,
      "wind_dir_deg": 67.5
    },
    {
      "battery_ok": 1,
      "channel": "C",
      "humidity": 50.0,
      "model": "Acurite-5n1",
      "observed_at": "2026-07-14 08:07:55 PDT",
      "rain_day_in": 0.0,
      "rain_mm": null,
      "rain_ytd_in": 46.682,
      "sensor_id": "1466",
      "temperature_c": null,
      "temperature_f": 74.8,
      "wind_avg_km_h": null,
      "wind_avg_mi_h": 0.0,
      "wind_dir_deg": 337.5
    },
    {
      "battery_ok": 1,
      "channel": "C",
      "humidity": 50.0,
      "model": "Acurite-5n1",
      "observed_at": "2026-07-14 08:02:55 PDT",
      "rain_day_in": 0.0,
      "rain_mm": null,
      "rain_ytd_in": 46.682,
      "sensor_id": "1466",
      "temperature_c": null,
      "temperature_f": 74.8,
      "wind_avg_km_h": null,
      "wind_avg_mi_h": 0.0,
      "wind_dir_deg": 0.0
    },
    {
      "battery_ok": 1,
      "channel": "C",
      "humidity": 50.0,
      "model": "Acurite-5n1",
      "observed_at": "2026-07-14 07:57:55 PDT",
      "rain_day_in": 0.0,
      "rain_mm": null,
      "rain_ytd_in": 46.682,
      "sensor_id": "1466",
      "temperature_c": null,
      "temperature_f": 74.7,
      "wind_avg_km_h": null,
      "wind_avg_mi_h": 0.0,
      "wind_dir_deg": 292.5
    },
    {
      "battery_ok": 1,
      "channel": "C",
      "humidity": 51.0,
      "model": "Acurite-5n1",
      "observed_at": "2026-07-14 07:52:55 PDT",
      "rain_day_in": 0.0,
      "rain_mm": null,
      "rain_ytd_in": 46.682,
      "sensor_id": "1466",
      "temperature_c": null,
      "temperature_f": 74.7,
      "wind_avg_km_h": null,
      "wind_avg_mi_h": 1.65,
      "wind_dir_deg": 292.5
    },
    {
      "battery_ok": 1,
      "channel": "C",
      "humidity": 47.0,
      "model": "Acurite-5n1",
      "observed_at": "2026-07-14 07:47:55 PDT",
      "rain_day_in": 0.0,
      "rain_mm": null,
      "rain_ytd_in": 46.682,
      "sensor_id": "1466",
      "temperature_c": null,
      "temperature_f": 74.7,
      "wind_avg_km_h": null,
      "wind_avg_mi_h": 1.136,
      "wind_dir_deg": 315.0
    },
    {
      "battery_ok": 1,
      "channel": "C",
      "humidity": 47.0,
      "model": "Acurite-5n1",
      "observed_at": "2026-07-14 07:42:55 PDT",
      "rain_day_in": 0.0,
      "rain_mm": null,
      "rain_ytd_in": 46.682,
      "sensor_id": "1466",
      "temperature_c": null,
      "temperature_f": 74.3,
      "wind_avg_km_h": null,
      "wind_avg_mi_h": 0.0,
      "wind_dir_deg": 67.5
    },
    {
      "battery_ok": 1,
      "channel": "C",
      "humidity": 49.0,
      "model": "Acurite-5n1",
      "observed_at": "2026-07-14 07:37:55 PDT",
      "rain_day_in": 0.0,
      "rain_mm": null,
      "rain_ytd_in": 46.682,
      "sensor_id": "1466",
      "temperature_c": null,
      "temperature_f": 73.8,
      "wind_avg_km_h": null,
      "wind_avg_mi_h": 0.0,
      "wind_dir_deg": 90.0
    },
    {
      "battery_ok": 1,
      "channel": "C",
      "humidity": 46.0,
      "model": "Acurite-5n1",
      "observed_at": "2026-07-14 07:32:55 PDT",
      "rain_day_in": 0.0,
      "rain_mm": null,
      "rain_ytd_in": 46.682,
      "sensor_id": "1466",
      "temperature_c": null,
      "temperature_f": 73.4,
      "wind_avg_km_h": null,
      "wind_avg_mi_h": 0.0,
      "wind_dir_deg": 90.0
    },
    {
      "battery_ok": 1,
      "channel": "C",
      "humidity": 44.0,
      "model": "Acurite-5n1",
      "observed_at": "2026-07-14 07:27:55 PDT",
      "rain_day_in": 0.0,
      "rain_mm": null,
      "rain_ytd_in": 46.682,
      "sensor_id": "1466",
      "temperature_c": null,
      "temperature_f": 73.0,
      "wind_avg_km_h": null,
      "wind_avg_mi_h": 0.0,
      "wind_dir_deg": 22.5
    },
    {
      "battery_ok": 1,
      "channel": "C",
      "humidity": 49.0,
      "model": "Acurite-5n1",
      "observed_at": "2026-07-14 07:22:55 PDT",
      "rain_day_in": 0.0,
      "rain_mm": null,
      "rain_ytd_in": 46.682,
      "sensor_id": "1466",
      "temperature_c": null,
      "temperature_f": 72.9,
      "wind_avg_km_h": null,
      "wind_avg_mi_h": 0.0,
      "wind_dir_deg": 315.0
    },
    {
      "battery_ok": 1,
      "channel": "C",
      "humidity": 45.0,
      "model": "Acurite-5n1",
      "observed_at": "2026-07-14 07:17:55 PDT",
      "rain_day_in": 0.0,
      "rain_mm": null,
      "rain_ytd_in": 46.682,
      "sensor_id": "1466",
      "temperature_c": null,
      "temperature_f": 72.5,
      "wind_avg_km_h": null,
      "wind_avg_mi_h": 0.0,
      "wind_dir_deg": 67.5
    },
    {
      "battery_ok": 1,
      "channel": "C",
      "humidity": 47.0,
      "model": "Acurite-5n1",
      "observed_at": "2026-07-14 07:12:55 PDT",
      "rain_day_in": 0.0,
      "rain_mm": null,
      "rain_ytd_in": 46.682,
      "sensor_id": "1466",
      "temperature_c": null,
      "temperature_f": 72.1,
      "wind_avg_km_h": null,
      "wind_avg_mi_h": 0.0,
      "wind_dir_deg": 22.5
    },
    {
      "battery_ok": 1,
      "channel": "C",
      "humidity": 48.0,
      "model": "Acurite-5n1",
      "observed_at": "2026-07-14 07:07:55 PDT",
      "rain_day_in": 0.0,
      "rain_mm": null,
      "rain_ytd_in": 46.682,
      "sensor_id": "1466",
      "temperature_c": null,
      "temperature_f": 72.0,
      "wind_avg_km_h": null,
      "wind_avg_mi_h": 0.0,
      "wind_dir_deg": 292.5
    },
    {
      "battery_ok": 1,
      "channel": "C",
      "humidity": 47.0,
      "model": "Acurite-5n1",
      "observed_at": "2026-07-14 07:02:55 PDT",
      "rain_day_in": 0.0,
      "rain_mm": null,
      "rain_ytd_in": 46.682,
      "sensor_id": "1466",
      "temperature_c": null,
      "temperature_f": 72.0,
      "wind_avg_km_h": null,
      "wind_avg_mi_h": 0.0,
      "wind_dir_deg": 292.5
    },
    {
      "battery_ok": 1,
      "channel": "C",
      "humidity": 47.0,
      "model": "Acurite-5n1",
      "observed_at": "2026-07-14 06:57:55 PDT",
      "rain_day_in": 0.0,
      "rain_mm": null,
      "rain_ytd_in": 46.682,
      "sensor_id": "1466",
      "temperature_c": null,
      "temperature_f": 72.1,
      "wind_avg_km_h": null,
      "wind_avg_mi_h": 0.0,
      "wind_dir_deg": 270.0
    },
    {
      "battery_ok": 1,
      "channel": "C",
      "humidity": 50.0,
      "model": "Acurite-5n1",
      "observed_at": "2026-07-14 06:52:55 PDT",
      "rain_day_in": 0.0,
      "rain_mm": null,
      "rain_ytd_in": 46.682,
      "sensor_id": "1466",
      "temperature_c": null,
      "temperature_f": 72.3,
      "wind_avg_km_h": null,
      "wind_avg_mi_h": 0.0,
      "wind_dir_deg": 315.0
    },
    {
      "battery_ok": 1,
      "channel": "C",
      "humidity": 47.0,
      "model": "Acurite-5n1",
      "observed_at": "2026-07-14 06:47:55 PDT",
      "rain_day_in": 0.0,
      "rain_mm": null,
      "rain_ytd_in": 46.682,
      "sensor_id": "1466",
      "temperature_c": null,
      "temperature_f": 72.5,
      "wind_avg_km_h": null,
      "wind_avg_mi_h": 1.65,
      "wind_dir_deg": 135.0
    },
    {
      "battery_ok": 1,
      "channel": "C",
      "humidity": 49.0,
      "model": "Acurite-5n1",
      "observed_at": "2026-07-14 06:42:55 PDT",
      "rain_day_in": 0.0,
      "rain_mm": null,
      "rain_ytd_in": 46.682,
      "sensor_id": "1466",
      "temperature_c": null,
      "temperature_f": 72.9,
      "wind_avg_km_h": null,
      "wind_avg_mi_h": 0.0,
      "wind_dir_deg": 112.5
    },
    {
      "battery_ok": 1,
      "channel": "C",
      "humidity": 49.0,
      "model": "Acurite-5n1",
      "observed_at": "2026-07-14 06:37:55 PDT",
      "rain_day_in": 0.0,
      "rain_mm": null,
      "rain_ytd_in": 46.682,
      "sensor_id": "1466",
      "temperature_c": null,
      "temperature_f": 73.8,
      "wind_avg_km_h": null,
      "wind_avg_mi_h": 0.0,
      "wind_dir_deg": 22.5
    },
    {
      "battery_ok": 1,
      "channel": "C",
      "humidity": 43.0,
      "model": "Acurite-5n1",
      "observed_at": "2026-07-14 06:32:55 PDT",
      "rain_day_in": 0.0,
      "rain_mm": null,
      "rain_ytd_in": 46.682,
      "sensor_id": "1466",
      "temperature_c": null,
      "temperature_f": 74.3,
      "wind_avg_km_h": null,
      "wind_avg_mi_h": 0.0,
      "wind_dir_deg": 202.5
    }
  ],
  "snapshot": {
    "battery_ok": 1,
    "channel": "C",
    "generated_at": "2026-07-14 08:30:29 PDT",
    "humidity": 57.0,
    "message_type": "49",
    "model": "Acurite-5n1",
    "observed_at": "2026-07-14 08:27:55 PDT",
    "rain_day_in": 0.0,
    "rain_in": 0.51,
    "rain_mm": null,
    "rain_ytd_in": 46.682,
    "sensor_id": "1466",
    "stale_minutes": 2,
    "temperature_c": null,
    "temperature_f": 74.7,
    "wind_avg_km_h": null,
    "wind_avg_mi_h": 0.0,
    "wind_dir_deg": 45.0
  }
}
